{
    "keep": {
        "days": false,
        "amount": 30
    },
    "auditLog": "D:\\bacnend -db\\express-prisma-api\\src\\logs\\debug\\.0a0c89f9697c22bb287f53edf4e374eba4bd6e43-audit.json",
    "files": [
        {
            "date": 1683010021747,
            "name": "D:\\bacnend -db\\express-prisma-api\\src\\logs\\debug\\2023-05-02.log",
            "hash": "8a8a75b804bdab5187aa41517735596267beb73369f57ab9eb6d5b43f6a3f347"
        },
        {
            "date": 1683104505259,
            "name": "D:\\bacnend -db\\express-prisma-api\\src\\logs\\debug\\2023-05-03.log",
            "hash": "ac90184d96bfa61fdd77e6f577b6027c352238bb458c33e602f282b987be537c"
        }
    ],
    "hashType": "sha256"
}